<archimate:ArchimateDiagramModel
    xmlns:xsi="http://www.w3.org/2001/XMLSchema-instance"
    xmlns:archimate="http://www.archimatetool.com/archimate"
    name="GEMMA Bedrijfsfunctiemodel"
    id="id-6ced183b53114f2d85c7e4040f9947bb">
  <children
      xsi:type="archimate:DiagramModelNote"
      id="id-b46710766a65488ba9ab7a7e74c9092f"
      font="1|arial|12.0|0|WINDOWS|1|0|0|0|0|0|0|0|0|1|0|0|0|0|arial"
      fontColor="#000000"
      lineColor="#000000"
      textAlignment="1"
      fillColor="#ffffff"
      content="Besturende functies">
    <bounds
        x="12"
        y="24"
        width="1507"
        height="120"/>
  </children>
  <children
      xsi:type="archimate:DiagramModelArchimateObject"
      id="id-7d9ed79039e148bdab0f1c5c4cbc04d6"
      font="1|Segoe UI|10.0|0|WINDOWS|1|0|0|0|0|0|0|0|0|1|0|0|0|0|Segoe UI"
      fontColor="#000000"
      lineColor="#000000"
      fillColor="#fff29b">
    <sourceConnections
        xsi:type="archimate:DiagramModelArchimateConnection"
        id="id-74820899c9094e5ab521495083214759"
        font="1|Segoe UI|9.0|0|WINDOWS|1|-15|0|0|0|0|0|0|0|0|3|2|1|34|Segoe UI"
        source="id-7d9ed79039e148bdab0f1c5c4cbc04d6"
        target="id-f6e805e04dd84994bc76f92b8ece2027">
      <archimateRelationship
          xsi:type="archimate:AggregationRelationship"
          href="AggregationRelationship_id-dc9b0f51bff245839f394ecbec5469f6.xml#id-dc9b0f51bff245839f394ecbec5469f6"/>
    </sourceConnections>
    <sourceConnections
        xsi:type="archimate:DiagramModelArchimateConnection"
        id="id-1a76b4f083cb43c0b3f25d74755d100c"
        font="1|Segoe UI|9.0|0|WINDOWS|1|-15|0|0|0|0|0|0|0|0|3|2|1|34|Segoe UI"
        source="id-7d9ed79039e148bdab0f1c5c4cbc04d6"
        target="id-deebdf858113452e9a2423820c579172">
      <archimateRelationship
          xsi:type="archimate:AggregationRelationship"
          href="AggregationRelationship_id-dd5865db462c4f2bb63d59b82a088bd1.xml#id-dd5865db462c4f2bb63d59b82a088bd1"/>
    </sourceConnections>
    <sourceConnections
        xsi:type="archimate:DiagramModelArchimateConnection"
        id="id-a2744d9b37824fe6a299daf372de5b0f"
        font="1|Segoe UI|9.0|0|WINDOWS|1|-15|0|0|0|0|0|0|0|0|3|2|1|34|Segoe UI"
        source="id-7d9ed79039e148bdab0f1c5c4cbc04d6"
        target="id-9e521cf676ed4473b4bb435ecdbaae53">
      <archimateRelationship
          xsi:type="archimate:AggregationRelationship"
          href="AggregationRelationship_id-a5434308d70047d08ca9a4c5fcce04ab.xml#id-a5434308d70047d08ca9a4c5fcce04ab"/>
    </sourceConnections>
    <sourceConnections
        xsi:type="archimate:DiagramModelArchimateConnection"
        id="id-e883c90e5f6849ac9fb4c667a73b849f"
        font="1|Segoe UI|9.0|0|WINDOWS|1|-15|0|0|0|0|0|0|0|0|3|2|1|34|Segoe UI"
        source="id-7d9ed79039e148bdab0f1c5c4cbc04d6"
        target="id-baa6d763853c42d9bb6e869e1022f9ae">
      <archimateRelationship
          xsi:type="archimate:AggregationRelationship"
          href="AggregationRelationship_id-7e0026b26475407485d0e460653f1a0b.xml#id-7e0026b26475407485d0e460653f1a0b"/>
    </sourceConnections>
    <bounds
        x="26"
        y="47"
        width="1480"
        height="87"/>
    <children
        xsi:type="archimate:DiagramModelArchimateObject"
        id="id-deebdf858113452e9a2423820c579172"
        targetConnections="id-1a76b4f083cb43c0b3f25d74755d100c"
        font="1|Segoe UI|9.0|0|WINDOWS|1|0|0|0|0|0|0|0|0|1|0|0|0|0|Segoe UI"
        fontColor="#000000"
        lineColor="#000000"
        fillColor="#ffbd9b">
      <bounds
          x="1246"
          y="19"
          width="193"
          height="53"/>
      <archimateElement
          xsi:type="archimate:BusinessFunction"
          href="BusinessFunction_id-c298942e658944c397333da451d9cf54.xml#id-c298942e658944c397333da451d9cf54"/>
    </children>
    <children
        xsi:type="archimate:DiagramModelArchimateObject"
        id="id-f6e805e04dd84994bc76f92b8ece2027"
        targetConnections="id-74820899c9094e5ab521495083214759"
        font="1|Segoe UI|9.0|0|WINDOWS|1|0|0|0|0|0|0|0|0|1|0|0|0|0|Segoe UI"
        fontColor="#000000"
        lineColor="#000000"
        fillColor="#ffbd9b">
      <bounds
          x="761"
          y="17"
          width="193"
          height="53"/>
      <archimateElement
          xsi:type="archimate:BusinessFunction"
          href="BusinessFunction_id-3f6a6371fb3a4761bab25dbb47b982fb.xml#id-3f6a6371fb3a4761bab25dbb47b982fb"/>
    </children>
    <children
        xsi:type="archimate:DiagramModelArchimateObject"
        id="id-baa6d763853c42d9bb6e869e1022f9ae"
        targetConnections="id-e883c90e5f6849ac9fb4c667a73b849f"
        font="1|Segoe UI|9.0|0|WINDOWS|1|0|0|0|0|0|0|0|0|1|0|0|0|0|Segoe UI"
        fontColor="#000000"
        lineColor="#000000"
        fillColor="#ffbd9b">
      <bounds
          x="518"
          y="17"
          width="193"
          height="53"/>
      <archimateElement
          xsi:type="archimate:BusinessFunction"
          href="BusinessFunction_id-95a51c178d3349edaacac0f59d168892.xml#id-95a51c178d3349edaacac0f59d168892"/>
    </children>
    <children
        xsi:type="archimate:DiagramModelArchimateObject"
        id="id-9e521cf676ed4473b4bb435ecdbaae53"
        targetConnections="id-a2744d9b37824fe6a299daf372de5b0f"
        font="1|Segoe UI|9.0|0|WINDOWS|1|0|0|0|0|0|0|0|0|1|0|0|0|0|Segoe UI"
        fontColor="#000000"
        lineColor="#000000"
        fillColor="#ecc1a3">
      <bounds
          x="33"
          y="17"
          width="193"
          height="53"/>
      <archimateElement
          xsi:type="archimate:BusinessFunction"
          href="BusinessFunction_id-85f7625fb69941818c85c7a53ece607f.xml#id-85f7625fb69941818c85c7a53ece607f"/>
    </children>
    <archimateElement
        xsi:type="archimate:BusinessFunction"
        href="BusinessFunction_id-23b9343132d04bab998f8b649a8f99d5.xml#id-23b9343132d04bab998f8b649a8f99d5"/>
  </children>
  <children
      xsi:type="archimate:DiagramModelNote"
      id="id-0f8019a753d6415694dcab7b7a6f6380"
      font="1|arial|12.0|0|WINDOWS|1|0|0|0|0|0|0|0|0|1|0|0|0|0|arial"
      fontColor="#000000"
      lineColor="#000000"
      textAlignment="1"
      fillColor="#ffffff"
      content="Primaire functies">
    <bounds
        x="12"
        y="154"
        width="1507"
        height="780"/>
  </children>
  <children
      xsi:type="archimate:DiagramModelArchimateObject"
      id="id-1618a5ef1de544e9acff2d81d548b1f9"
      font="1|Segoe UI|10.0|0|WINDOWS|1|0|0|0|0|0|0|0|0|1|0|0|0|0|Segoe UI"
      fontColor="#000000"
      lineColor="#000000"
      fillColor="#fff29b">
    <sourceConnections
        xsi:type="archimate:DiagramModelArchimateConnection"
        id="id-2a11f74e67274b02abb737c3101c441d"
        font="1|Segoe UI|9.0|0|WINDOWS|1|-15|0|0|0|0|0|0|0|0|3|2|1|34|Segoe UI"
        source="id-1618a5ef1de544e9acff2d81d548b1f9"
        target="id-7202182b239741c9bdd472e7529e74e1">
      <archimateRelationship
          xsi:type="archimate:AggregationRelationship"
          href="AggregationRelationship_id-53b30ab8e01842e780a2c25270cd3add.xml#id-53b30ab8e01842e780a2c25270cd3add"/>
    </sourceConnections>
    <sourceConnections
        xsi:type="archimate:DiagramModelArchimateConnection"
        id="id-7596fcdd2b1748f79bcdbf80b0f25360"
        font="1|Segoe UI|9.0|0|WINDOWS|1|-15|0|0|0|0|0|0|0|0|3|2|1|34|Segoe UI"
        source="id-1618a5ef1de544e9acff2d81d548b1f9"
        target="id-52a2dcb2c5a946cb8444b53861ff7462">
      <archimateRelationship
          xsi:type="archimate:AggregationRelationship"
          href="AggregationRelationship_id-e6026f1d650645058395c8472eafd3ac.xml#id-e6026f1d650645058395c8472eafd3ac"/>
    </sourceConnections>
    <sourceConnections
        xsi:type="archimate:DiagramModelArchimateConnection"
        id="id-d36211188bba431c9fc8b76e638dd45d"
        font="1|Segoe UI|9.0|0|WINDOWS|1|-15|0|0|0|0|0|0|0|0|3|2|1|34|Segoe UI"
        source="id-1618a5ef1de544e9acff2d81d548b1f9"
        target="id-1bc4522f6a4346bd969ebc8db6e88f48">
      <archimateRelationship
          xsi:type="archimate:AggregationRelationship"
          href="AggregationRelationship_id-479d1172f249434282fe1c3ecb5df5f6.xml#id-479d1172f249434282fe1c3ecb5df5f6"/>
    </sourceConnections>
    <sourceConnections
        xsi:type="archimate:DiagramModelArchimateConnection"
        id="id-c33f5cb04b09454faf717181c85e39c5"
        font="1|Segoe UI|9.0|0|WINDOWS|1|-15|0|0|0|0|0|0|0|0|3|2|1|34|Segoe UI"
        source="id-1618a5ef1de544e9acff2d81d548b1f9"
        target="id-74414f20b9034956943213af6f66f4bf">
      <archimateRelationship
          xsi:type="archimate:AggregationRelationship"
          href="AggregationRelationship_id-d5e73e9e6f5442119c68cf688d50bfc0.xml#id-d5e73e9e6f5442119c68cf688d50bfc0"/>
    </sourceConnections>
    <sourceConnections
        xsi:type="archimate:DiagramModelArchimateConnection"
        id="id-dd43d24507eb44d58bb70036b97e6ac0"
        font="1|Segoe UI|9.0|0|WINDOWS|1|-15|0|0|0|0|0|0|0|0|3|2|1|34|Segoe UI"
        source="id-1618a5ef1de544e9acff2d81d548b1f9"
        target="id-ddd46761a4a343a099623f0d24390cf0">
      <archimateRelationship
          xsi:type="archimate:AggregationRelationship"
          href="AggregationRelationship_id-e09caf9308934cc8bad5a59420488c6c.xml#id-e09caf9308934cc8bad5a59420488c6c"/>
    </sourceConnections>
    <sourceConnections
        xsi:type="archimate:DiagramModelArchimateConnection"
        id="id-18cd2e9949444b25b4450b3011fec422"
        font="1|Segoe UI|9.0|0|WINDOWS|1|-15|0|0|0|0|0|0|0|0|3|2|1|34|Segoe UI"
        source="id-1618a5ef1de544e9acff2d81d548b1f9"
        target="id-1dafbd20c07041feae68a553f00269d8">
      <archimateRelationship
          xsi:type="archimate:AggregationRelationship"
          href="AggregationRelationship_id-c714b682e41045a1b4b5aa9709688d8f.xml#id-c714b682e41045a1b4b5aa9709688d8f"/>
    </sourceConnections>
    <sourceConnections
        xsi:type="archimate:DiagramModelArchimateConnection"
        id="id-6c45856e56794d97b41b077f339d815d"
        font="1|Segoe UI|9.0|0|WINDOWS|1|-15|0|0|0|0|0|0|0|0|3|2|1|34|Segoe UI"
        source="id-1618a5ef1de544e9acff2d81d548b1f9"
        target="id-3922b0667f6c4e2d8a622b397c1d3962">
      <archimateRelationship
          xsi:type="archimate:AggregationRelationship"
          href="AggregationRelationship_id-17bfde9f2c24470289195d9a83271100.xml#id-17bfde9f2c24470289195d9a83271100"/>
    </sourceConnections>
    <sourceConnections
        xsi:type="archimate:DiagramModelArchimateConnection"
        id="id-87e7b8bb5b7a4864bfd08dd03510f434"
        font="1|Segoe UI|9.0|0|WINDOWS|1|-15|0|0|0|0|0|0|0|0|3|2|1|34|Segoe UI"
        source="id-1618a5ef1de544e9acff2d81d548b1f9"
        target="id-fe2b0fb7126042b5be0b821b80f1ecc3">
      <archimateRelationship
          xsi:type="archimate:AggregationRelationship"
          href="AggregationRelationship_id-e84710a8ce984bfe832fb2c4e1931349.xml#id-e84710a8ce984bfe832fb2c4e1931349"/>
    </sourceConnections>
    <bounds
        x="26"
        y="462"
        width="1480"
        height="153"/>
    <children
        xsi:type="archimate:DiagramModelArchimateObject"
        id="id-52a2dcb2c5a946cb8444b53861ff7462"
        targetConnections="id-7596fcdd2b1748f79bcdbf80b0f25360"
        font="1|Segoe UI|9.0|0|WINDOWS|1|0|0|0|0|0|0|0|0|1|0|0|0|0|Segoe UI"
        fontColor="#000000"
        lineColor="#000000"
        fillColor="#ffffcc">
      <bounds
          x="518"
          y="20"
          width="193"
          height="53"/>
      <archimateElement
          xsi:type="archimate:BusinessFunction"
          href="BusinessFunction_id-85bacd96f4524af8972654e93f8de89f.xml#id-85bacd96f4524af8972654e93f8de89f"/>
    </children>
    <children
        xsi:type="archimate:DiagramModelArchimateObject"
        id="id-3922b0667f6c4e2d8a622b397c1d3962"
        targetConnections="id-6c45856e56794d97b41b077f339d815d"
        font="1|Segoe UI|9.0|0|WINDOWS|1|0|0|0|0|0|0|0|0|1|0|0|0|0|Segoe UI"
        fontColor="#000000"
        lineColor="#000000"
        fillColor="#ffffcc">
      <bounds
          x="1246"
          y="82"
          width="193"
          height="53"/>
      <archimateElement
          xsi:type="archimate:BusinessFunction"
          href="BusinessFunction_id-d3f3932cc9d8402ead617b1db9d07620.xml#id-d3f3932cc9d8402ead617b1db9d07620"/>
    </children>
    <children
        xsi:type="archimate:DiagramModelArchimateObject"
        id="id-fe2b0fb7126042b5be0b821b80f1ecc3"
        targetConnections="id-87e7b8bb5b7a4864bfd08dd03510f434"
        font="1|Segoe UI|9.0|0|WINDOWS|1|0|0|0|0|0|0|0|0|1|0|0|0|0|Segoe UI"
        fontColor="#000000"
        lineColor="#000000"
        fillColor="#ffffcc">
      <bounds
          x="1246"
          y="18"
          width="193"
          height="53"/>
      <archimateElement
          xsi:type="archimate:BusinessFunction"
          href="BusinessFunction_id-5d7724b998ea4540a414eb89787b9688.xml#id-5d7724b998ea4540a414eb89787b9688"/>
    </children>
    <children
        xsi:type="archimate:DiagramModelArchimateObject"
        id="id-7202182b239741c9bdd472e7529e74e1"
        targetConnections="id-2a11f74e67274b02abb737c3101c441d"
        font="1|Segoe UI|9.0|0|WINDOWS|1|0|0|0|0|0|0|0|0|1|0|0|0|0|Segoe UI"
        fontColor="#000000"
        lineColor="#000000"
        fillColor="#ffffcc">
      <bounds
          x="33"
          y="20"
          width="193"
          height="53"/>
      <archimateElement
          xsi:type="archimate:BusinessFunction"
          href="BusinessFunction_id-9c688ff6c5de41c8b14d22f328c898be.xml#id-9c688ff6c5de41c8b14d22f328c898be"/>
    </children>
    <children
        xsi:type="archimate:DiagramModelArchimateObject"
        id="id-ddd46761a4a343a099623f0d24390cf0"
        targetConnections="id-dd43d24507eb44d58bb70036b97e6ac0"
        font="1|Segoe UI|9.0|0|WINDOWS|1|0|0|0|0|0|0|0|0|1|0|0|0|0|Segoe UI"
        fontColor="#000000"
        lineColor="#000000"
        fillColor="#ffffcc">
      <bounds
          x="518"
          y="83"
          width="193"
          height="53"/>
      <archimateElement
          xsi:type="archimate:BusinessFunction"
          href="BusinessFunction_id-930e2c1688f94c918417108267bb5979.xml#id-930e2c1688f94c918417108267bb5979"/>
    </children>
    <children
        xsi:type="archimate:DiagramModelArchimateObject"
        id="id-74414f20b9034956943213af6f66f4bf"
        targetConnections="id-c33f5cb04b09454faf717181c85e39c5"
        font="1|Segoe UI|9.0|0|WINDOWS|1|0|0|0|0|0|0|0|0|1|0|0|0|0|Segoe UI"
        fontColor="#000000"
        lineColor="#000000"
        fillColor="#ffffcc">
      <bounds
          x="761"
          y="83"
          width="193"
          height="53"/>
      <archimateElement
          xsi:type="archimate:BusinessFunction"
          href="BusinessFunction_id-4b647267b2df4daf9d33ff2561c0151e.xml#id-4b647267b2df4daf9d33ff2561c0151e"/>
    </children>
    <children
        xsi:type="archimate:DiagramModelArchimateObject"
        id="id-1bc4522f6a4346bd969ebc8db6e88f48"
        targetConnections="id-d36211188bba431c9fc8b76e638dd45d"
        font="1|Segoe UI|9.0|0|WINDOWS|1|0|0|0|0|0|0|0|0|1|0|0|0|0|Segoe UI"
        fontColor="#000000"
        lineColor="#000000"
        fillColor="#ffffcc">
      <bounds
          x="33"
          y="83"
          width="193"
          height="53"/>
      <archimateElement
          xsi:type="archimate:BusinessFunction"
          href="BusinessFunction_id-96fa16f8c09b4c9892286d1e7464fcac.xml#id-96fa16f8c09b4c9892286d1e7464fcac"/>
    </children>
    <children
        xsi:type="archimate:DiagramModelArchimateObject"
        id="id-1dafbd20c07041feae68a553f00269d8"
        targetConnections="id-18cd2e9949444b25b4450b3011fec422"
        font="1|Segoe UI|9.0|0|WINDOWS|1|0|0|0|0|0|0|0|0|1|0|0|0|0|Segoe UI"
        fontColor="#000000"
        lineColor="#000000"
        fillColor="#ffffcc">
      <bounds
          x="761"
          y="20"
          width="193"
          height="53"/>
      <archimateElement
          xsi:type="archimate:BusinessFunction"
          href="BusinessFunction_id-f38e7198487c4c2aa148b99c7f6361ec.xml#id-f38e7198487c4c2aa148b99c7f6361ec"/>
    </children>
    <archimateElement
        xsi:type="archimate:BusinessFunction"
        href="BusinessFunction_id-2db08ceb901544c4bd80d5adadadbacb.xml#id-2db08ceb901544c4bd80d5adadadbacb"/>
  </children>
  <children
      xsi:type="archimate:DiagramModelArchimateObject"
      id="id-11392450e6d64102be6440fde6cc6020"
      font="1|Segoe UI|10.0|0|WINDOWS|1|0|0|0|0|0|0|0|0|1|0|0|0|0|Segoe UI"
      fontColor="#000000"
      lineColor="#000000"
      fillColor="#fff29b">
    <sourceConnections
        xsi:type="archimate:DiagramModelArchimateConnection"
        id="id-385c88c39cc64e58bb23fdc2c855a15e"
        font="1|Segoe UI|9.0|0|WINDOWS|1|-15|0|0|0|0|0|0|0|0|3|2|1|34|Segoe UI"
        source="id-11392450e6d64102be6440fde6cc6020"
        target="id-aac38389adf1492bbf9cfe5c2e235f25">
      <archimateRelationship
          xsi:type="archimate:AggregationRelationship"
          href="AggregationRelationship_id-3d1a404f474c4b599d2b0b067aef82ab.xml#id-3d1a404f474c4b599d2b0b067aef82ab"/>
    </sourceConnections>
    <sourceConnections
        xsi:type="archimate:DiagramModelArchimateConnection"
        id="id-a83d65dd93ef482abdd704220c39a3a5"
        font="1|Segoe UI|9.0|0|WINDOWS|1|-15|0|0|0|0|0|0|0|0|3|2|1|34|Segoe UI"
        source="id-11392450e6d64102be6440fde6cc6020"
        target="id-954196915c244c878a3c62358b0868c1">
      <archimateRelationship
          xsi:type="archimate:AggregationRelationship"
          href="AggregationRelationship_id-78a316b78145410c9d2fda0c37f0b252.xml#id-78a316b78145410c9d2fda0c37f0b252"/>
    </sourceConnections>
    <sourceConnections
        xsi:type="archimate:DiagramModelArchimateConnection"
        id="id-8ffcbf4bc6b1450994f70de96cb1b86d"
        font="1|Segoe UI|9.0|0|WINDOWS|1|-15|0|0|0|0|0|0|0|0|3|2|1|34|Segoe UI"
        source="id-11392450e6d64102be6440fde6cc6020"
        target="id-e7a155c673024b7f8e74674027b88f6a">
      <archimateRelationship
          xsi:type="archimate:AggregationRelationship"
          href="AggregationRelationship_id-9bb73b5a4fcc4fb594a909a2a5d46923.xml#id-9bb73b5a4fcc4fb594a909a2a5d46923"/>
    </sourceConnections>
    <sourceConnections
        xsi:type="archimate:DiagramModelArchimateConnection"
        id="id-d5e909c9950e457e9039288ba9bdbfa1"
        font="1|Segoe UI|9.0|0|WINDOWS|1|-15|0|0|0|0|0|0|0|0|3|2|1|34|Segoe UI"
        source="id-11392450e6d64102be6440fde6cc6020"
        target="id-fd3f3d3c21eb45bdb2c10e464d8d90cd">
      <archimateRelationship
          xsi:type="archimate:AggregationRelationship"
          href="AggregationRelationship_id-caf60ad985a4493c81227b5c295e0e2d.xml#id-caf60ad985a4493c81227b5c295e0e2d"/>
    </sourceConnections>
    <sourceConnections
        xsi:type="archimate:DiagramModelArchimateConnection"
        id="id-310d6957c2674078b55ec0d7eeeda218"
        font="1|Segoe UI|9.0|0|WINDOWS|1|-15|0|0|0|0|0|0|0|0|3|2|1|34|Segoe UI"
        source="id-11392450e6d64102be6440fde6cc6020"
        target="id-3b11e9e1c04940b6a895f394b370e71b">
      <archimateRelationship
          xsi:type="archimate:AggregationRelationship"
          href="AggregationRelationship_id-fc0c5e00a8844aa59ba2b4a1cce0bf41.xml#id-fc0c5e00a8844aa59ba2b4a1cce0bf41"/>
    </sourceConnections>
    <sourceConnections
        xsi:type="archimate:DiagramModelArchimateConnection"
        id="id-7cc8420811bb4929bceedd72f719cd1b"
        font="1|Segoe UI|9.0|0|WINDOWS|1|-15|0|0|0|0|0|0|0|0|3|2|1|34|Segoe UI"
        source="id-11392450e6d64102be6440fde6cc6020"
        target="id-f4044da940ed44ae81c74b37da387c1c">
      <archimateRelationship
          xsi:type="archimate:AggregationRelationship"
          href="AggregationRelationship_id-d839c3d4d1d94819992ae584add1e31a.xml#id-d839c3d4d1d94819992ae584add1e31a"/>
    </sourceConnections>
    <bounds
        x="26"
        y="181"
        width="1480"
        height="87"/>
    <children
        xsi:type="archimate:DiagramModelArchimateObject"
        id="id-e7a155c673024b7f8e74674027b88f6a"
        targetConnections="id-8ffcbf4bc6b1450994f70de96cb1b86d"
        font="1|Segoe UI|9.0|0|WINDOWS|1|0|0|0|0|0|0|0|0|1|0|0|0|0|Segoe UI"
        fontColor="#000000"
        lineColor="#000000"
        fillColor="#f4c0a0">
      <bounds
          x="1246"
          y="19"
          width="193"
          height="53"/>
      <archimateElement
          xsi:type="archimate:BusinessFunction"
          href="BusinessFunction_id-8d9ce2e0bb244d548ad90a3664dc75cf.xml#id-8d9ce2e0bb244d548ad90a3664dc75cf"/>
    </children>
    <children
        xsi:type="archimate:DiagramModelArchimateObject"
        id="id-fd3f3d3c21eb45bdb2c10e464d8d90cd"
        targetConnections="id-d5e909c9950e457e9039288ba9bdbfa1"
        font="1|Segoe UI|9.0|0|WINDOWS|1|0|0|0|0|0|0|0|0|1|0|0|0|0|Segoe UI"
        fontColor="#000000"
        lineColor="#000000"
        fillColor="#f4c0a0">
      <bounds
          x="1004"
          y="21"
          width="193"
          height="53"/>
      <archimateElement
          xsi:type="archimate:BusinessFunction"
          href="BusinessFunction_id-fec0a94427e249b2934e52e2e43e05a5.xml#id-fec0a94427e249b2934e52e2e43e05a5"/>
    </children>
    <children
        xsi:type="archimate:DiagramModelArchimateObject"
        id="id-954196915c244c878a3c62358b0868c1"
        targetConnections="id-a83d65dd93ef482abdd704220c39a3a5"
        font="1|Segoe UI|9.0|0|WINDOWS|1|0|0|0|0|0|0|0|0|1|0|0|0|0|Segoe UI"
        fontColor="#000000"
        lineColor="#000000"
        fillColor="#f4c0a0">
      <bounds
          x="761"
          y="21"
          width="193"
          height="53"/>
      <archimateElement
          xsi:type="archimate:BusinessFunction"
          href="BusinessFunction_id-e62eb2b542a24df6a46436ae4642a5f0.xml#id-e62eb2b542a24df6a46436ae4642a5f0"/>
    </children>
    <children
        xsi:type="archimate:DiagramModelArchimateObject"
        id="id-3b11e9e1c04940b6a895f394b370e71b"
        targetConnections="id-310d6957c2674078b55ec0d7eeeda218"
        font="1|Segoe UI|9.0|0|WINDOWS|1|0|0|0|0|0|0|0|0|1|0|0|0|0|Segoe UI"
        fontColor="#000000"
        lineColor="#000000"
        fillColor="#f4c0a0">
      <bounds
          x="518"
          y="21"
          width="193"
          height="53"/>
      <archimateElement
          xsi:type="archimate:BusinessFunction"
          href="BusinessFunction_id-611c2e01aa624fde937824754ac5e792.xml#id-611c2e01aa624fde937824754ac5e792"/>
    </children>
    <children
        xsi:type="archimate:DiagramModelArchimateObject"
        id="id-aac38389adf1492bbf9cfe5c2e235f25"
        targetConnections="id-385c88c39cc64e58bb23fdc2c855a15e"
        font="1|Segoe UI|9.0|0|WINDOWS|1|0|0|0|0|0|0|0|0|1|0|0|0|0|Segoe UI"
        fontColor="#000000"
        lineColor="#000000"
        fillColor="#ecc1a3">
      <bounds
          x="276"
          y="21"
          width="193"
          height="53"/>
      <archimateElement
          xsi:type="archimate:BusinessFunction"
          href="BusinessFunction_id-9fbe448b47af40a5be7fd0971a89e0a7.xml#id-9fbe448b47af40a5be7fd0971a89e0a7"/>
    </children>
    <children
        xsi:type="archimate:DiagramModelArchimateObject"
        id="id-f4044da940ed44ae81c74b37da387c1c"
        targetConnections="id-7cc8420811bb4929bceedd72f719cd1b"
        font="1|Segoe UI|9.0|0|WINDOWS|1|0|0|0|0|0|0|0|0|1|0|0|0|0|Segoe UI"
        fontColor="#000000"
        lineColor="#000000"
        fillColor="#e5c1a7">
      <bounds
          x="33"
          y="21"
          width="193"
          height="53"/>
      <archimateElement
          xsi:type="archimate:BusinessFunction"
          href="BusinessFunction_id-0ec0306424e943b7b6d5f65fbac1823e.xml#id-0ec0306424e943b7b6d5f65fbac1823e"/>
    </children>
    <archimateElement
        xsi:type="archimate:BusinessFunction"
        href="BusinessFunction_id-94c6e9c2efde4a1c8f0c1ff7e01be0d4.xml#id-94c6e9c2efde4a1c8f0c1ff7e01be0d4"/>
  </children>
  <children
      xsi:type="archimate:DiagramModelArchimateObject"
      id="id-1af095b685f8415b9ebe5fc6321ab03b"
      font="1|Segoe UI|10.0|0|WINDOWS|1|0|0|0|0|0|0|0|0|1|0|0|0|0|Segoe UI"
      fontColor="#000000"
      lineColor="#000000"
      fillColor="#fff29b">
    <sourceConnections
        xsi:type="archimate:DiagramModelArchimateConnection"
        id="id-90a4f40499164050857f2f5f14d63ccc"
        font="1|Segoe UI|9.0|0|WINDOWS|1|-15|0|0|0|0|0|0|0|0|3|2|1|34|Segoe UI"
        source="id-1af095b685f8415b9ebe5fc6321ab03b"
        target="id-86e04eba8e844275b79ab2ed5a6e1a35">
      <archimateRelationship
          xsi:type="archimate:AggregationRelationship"
          href="AggregationRelationship_id-2aae6b2954d84156a00439d9115126c4.xml#id-2aae6b2954d84156a00439d9115126c4"/>
    </sourceConnections>
    <sourceConnections
        xsi:type="archimate:DiagramModelArchimateConnection"
        id="id-49169014e7b5447d96236c27fe5ec841"
        font="1|Segoe UI|9.0|0|WINDOWS|1|-15|0|0|0|0|0|0|0|0|3|2|1|34|Segoe UI"
        source="id-1af095b685f8415b9ebe5fc6321ab03b"
        target="id-7344897a0ba74cd8b5c0f574706ad950">
      <archimateRelationship
          xsi:type="archimate:AggregationRelationship"
          href="AggregationRelationship_id-6d2311a1535e445f9985b682dc532424.xml#id-6d2311a1535e445f9985b682dc532424"/>
    </sourceConnections>
    <sourceConnections
        xsi:type="archimate:DiagramModelArchimateConnection"
        id="id-aa37102eabfb44c6b860752b5f7c6442"
        font="1|Segoe UI|9.0|0|WINDOWS|1|-15|0|0|0|0|0|0|0|0|3|2|1|34|Segoe UI"
        source="id-1af095b685f8415b9ebe5fc6321ab03b"
        target="id-7982cc1be95040e9bfe2a2c2f222a42c">
      <archimateRelationship
          xsi:type="archimate:AggregationRelationship"
          href="AggregationRelationship_id-23d4e396afc540a3a0dd311a5f206e03.xml#id-23d4e396afc540a3a0dd311a5f206e03"/>
    </sourceConnections>
    <sourceConnections
        xsi:type="archimate:DiagramModelArchimateConnection"
        id="id-df16f713bbc845ebb719fe4d70cb83e7"
        font="1|Segoe UI|9.0|0|WINDOWS|1|-15|0|0|0|0|0|0|0|0|3|2|1|34|Segoe UI"
        source="id-1af095b685f8415b9ebe5fc6321ab03b"
        target="id-396b786ab31e4b04961660968f880d19">
      <archimateRelationship
          xsi:type="archimate:AggregationRelationship"
          href="AggregationRelationship_id-f19dba4d492e4acdabe4f893c040a5f9.xml#id-f19dba4d492e4acdabe4f893c040a5f9"/>
    </sourceConnections>
    <bounds
        x="26"
        y="622"
        width="1480"
        height="307"/>
    <children
        xsi:type="archimate:DiagramModelArchimateObject"
        id="id-1babe1c43c2b4a39b5f10096088bdbc7"
        font="1|Segoe UI|9.0|0|WINDOWS|1|0|0|0|0|0|0|0|0|1|0|0|0|0|Segoe UI"
        fontColor="#000000"
        lineColor="#000000"
        fillColor="#ffffcc">
      <bounds
          x="13"
          y="246"
          width="1447"
          height="47"/>
      <archimateElement
          xsi:type="archimate:BusinessFunction"
          href="BusinessFunction_id-f9f55fa6f7714108ac7c1cd5d1fa27b4.xml#id-f9f55fa6f7714108ac7c1cd5d1fa27b4"/>
    </children>
    <children
        xsi:type="archimate:DiagramModelArchimateObject"
        id="id-86e04eba8e844275b79ab2ed5a6e1a35"
        targetConnections="id-90a4f40499164050857f2f5f14d63ccc"
        font="1|Segoe UI|9.0|0|WINDOWS|1|0|0|0|0|0|0|0|0|1|0|0|0|0|Segoe UI"
        fontColor="#000000"
        lineColor="#000000"
        fillColor="#fff8b7">
      <sourceConnections
          xsi:type="archimate:DiagramModelArchimateConnection"
          id="id-d752d53d7e4f48aaa3091d3c473fc856"
          font="1|Segoe UI|9.0|0|WINDOWS|1|-15|0|0|0|0|0|0|0|0|3|2|1|34|Segoe UI"
          source="id-86e04eba8e844275b79ab2ed5a6e1a35"
          target="id-2985dbdfad0941ee97643b651c0770d9">
        <archimateRelationship
            xsi:type="archimate:AggregationRelationship"
            href="AggregationRelationship_id-abb580f929e847fdb391a9b92d1c09f1.xml#id-abb580f929e847fdb391a9b92d1c09f1"/>
      </sourceConnections>
      <sourceConnections
          xsi:type="archimate:DiagramModelArchimateConnection"
          id="id-bf16aa3e5f5e40da94064974aca6d420"
          font="1|Segoe UI|9.0|0|WINDOWS|1|-15|0|0|0|0|0|0|0|0|3|2|1|34|Segoe UI"
          source="id-86e04eba8e844275b79ab2ed5a6e1a35"
          target="id-091ee8910ff6439ebe9ae216cd62e685">
        <archimateRelationship
            xsi:type="archimate:AggregationRelationship"
            href="AggregationRelationship_id-23a5a0ea5f0f46a79360294e3dea8ff5.xml#id-23a5a0ea5f0f46a79360294e3dea8ff5"/>
      </sourceConnections>
      <sourceConnections
          xsi:type="archimate:DiagramModelArchimateConnection"
          id="id-57f623f9aa7b42a69616f8d28d678f70"
          font="1|Segoe UI|9.0|0|WINDOWS|1|-15|0|0|0|0|0|0|0|0|3|2|1|34|Segoe UI"
          source="id-86e04eba8e844275b79ab2ed5a6e1a35"
          target="id-be0f222aa58e45e58c1f88c17f919a65">
        <archimateRelationship
            xsi:type="archimate:AggregationRelationship"
            href="AggregationRelationship_id-e0937cba376a4cfb906c243f42ba85e9.xml#id-e0937cba376a4cfb906c243f42ba85e9"/>
      </sourceConnections>
      <sourceConnections
          xsi:type="archimate:DiagramModelArchimateConnection"
          id="id-8c41fcdf4d47451080ab9769536c0060"
          font="1|Segoe UI|9.0|0|WINDOWS|1|-15|0|0|0|0|0|0|0|0|3|2|1|34|Segoe UI"
          source="id-86e04eba8e844275b79ab2ed5a6e1a35"
          target="id-9d43c438d7f0466c9915293bcdc90e43">
        <archimateRelationship
            xsi:type="archimate:AggregationRelationship"
            href="AggregationRelationship_id-def7610f758a4d41b6b016651c77dcd6.xml#id-def7610f758a4d41b6b016651c77dcd6"/>
      </sourceConnections>
      <bounds
          x="13"
          y="26"
          width="347"
          height="213"/>
      <children
          xsi:type="archimate:DiagramModelArchimateObject"
          id="id-be0f222aa58e45e58c1f88c17f919a65"
          targetConnections="id-57f623f9aa7b42a69616f8d28d678f70"
          font="1|Segoe UI|9.0|0|WINDOWS|1|0|0|0|0|0|0|0|0|1|0|0|0|0|Segoe UI"
          fontColor="#000000"
          lineColor="#000000"
          fillColor="#ffffcc">
        <bounds
            x="180"
            y="87"
            width="147"
            height="53"/>
        <archimateElement
            xsi:type="archimate:BusinessFunction"
            href="BusinessFunction_id-ff0608446a2d45af841c23791367a7e5.xml#id-ff0608446a2d45af841c23791367a7e5"/>
      </children>
      <children
          xsi:type="archimate:DiagramModelArchimateObject"
          id="id-2985dbdfad0941ee97643b651c0770d9"
          targetConnections="id-d752d53d7e4f48aaa3091d3c473fc856"
          font="1|Segoe UI|9.0|0|WINDOWS|1|0|0|0|0|0|0|0|0|1|0|0|0|0|Segoe UI"
          fontColor="#000000"
          lineColor="#000000"
          fillColor="#ffffcc">
        <bounds
            x="180"
            y="27"
            width="147"
            height="53"/>
        <archimateElement
            xsi:type="archimate:BusinessFunction"
            href="BusinessFunction_id-8ae831e57a47413eb5698fe83035fc4d.xml#id-8ae831e57a47413eb5698fe83035fc4d"/>
      </children>
      <children
          xsi:type="archimate:DiagramModelArchimateObject"
          id="id-091ee8910ff6439ebe9ae216cd62e685"
          targetConnections="id-bf16aa3e5f5e40da94064974aca6d420"
          font="1|Segoe UI|9.0|0|WINDOWS|1|0|0|0|0|0|0|0|0|1|0|0|0|0|Segoe UI"
          fontColor="#000000"
          lineColor="#000000"
          fillColor="#ffffcc">
        <bounds
            x="16"
            y="88"
            width="147"
            height="53"/>
        <archimateElement
            xsi:type="archimate:BusinessFunction"
            href="BusinessFunction_id-a91de4b12de64f6eb7ff682720388ca6.xml#id-a91de4b12de64f6eb7ff682720388ca6"/>
      </children>
      <children
          xsi:type="archimate:DiagramModelArchimateObject"
          id="id-9d43c438d7f0466c9915293bcdc90e43"
          targetConnections="id-8c41fcdf4d47451080ab9769536c0060"
          font="1|Segoe UI|9.0|0|WINDOWS|1|0|0|0|0|0|0|0|0|1|0|0|0|0|Segoe UI"
          fontColor="#000000"
          lineColor="#000000"
          fillColor="#ffffcc">
        <bounds
            x="18"
            y="27"
            width="147"
            height="53"/>
        <archimateElement
            xsi:type="archimate:BusinessFunction"
            href="BusinessFunction_id-d81369075ffc444ab0680fe9b4ca60f3.xml#id-d81369075ffc444ab0680fe9b4ca60f3"/>
      </children>
      <archimateElement
          xsi:type="archimate:BusinessFunction"
          href="BusinessFunction_id-01ed27d7dbe1445eb7d9fe6daf7027ef.xml#id-01ed27d7dbe1445eb7d9fe6daf7027ef"/>
    </children>
    <children
        xsi:type="archimate:DiagramModelArchimateObject"
        id="id-7344897a0ba74cd8b5c0f574706ad950"
        targetConnections="id-49169014e7b5447d96236c27fe5ec841"
        font="1|Segoe UI|9.0|0|WINDOWS|1|0|0|0|0|0|0|0|0|1|0|0|0|0|Segoe UI"
        fontColor="#000000"
        lineColor="#000000"
        fillColor="#fff8b7">
      <sourceConnections
          xsi:type="archimate:DiagramModelArchimateConnection"
          id="id-b7c59e36e5fe4c58806d3b5156dc74f1"
          font="1|Segoe UI|9.0|0|WINDOWS|1|-15|0|0|0|0|0|0|0|0|3|2|1|34|Segoe UI"
          source="id-7344897a0ba74cd8b5c0f574706ad950"
          target="id-961a8f3bdae84b9298c092753c2062b5">
        <archimateRelationship
            xsi:type="archimate:AggregationRelationship"
            href="AggregationRelationship_id-22e6dfdb2f18423c8b3fafa4e3fe2943.xml#id-22e6dfdb2f18423c8b3fafa4e3fe2943"/>
      </sourceConnections>
      <sourceConnections
          xsi:type="archimate:DiagramModelArchimateConnection"
          id="id-67d1cc32146d4f9094a7be9f589651fa"
          font="1|Segoe UI|9.0|0|WINDOWS|1|-15|0|0|0|0|0|0|0|0|3|2|1|34|Segoe UI"
          source="id-7344897a0ba74cd8b5c0f574706ad950"
          target="id-efabed6086994fe28a676db36d924968">
        <archimateRelationship
            xsi:type="archimate:AggregationRelationship"
            href="AggregationRelationship_id-784e3426e5fa466496a3e371cd058195.xml#id-784e3426e5fa466496a3e371cd058195"/>
      </sourceConnections>
      <sourceConnections
          xsi:type="archimate:DiagramModelArchimateConnection"
          id="id-9154b013c96a4d908ea5212fd5b4557f"
          font="1|Segoe UI|9.0|0|WINDOWS|1|-15|0|0|0|0|0|0|0|0|3|2|1|34|Segoe UI"
          source="id-7344897a0ba74cd8b5c0f574706ad950"
          target="id-90391b9c874149a39d6aa6ad43cbf1be">
        <archimateRelationship
            xsi:type="archimate:AggregationRelationship"
            href="AggregationRelationship_id-fa888b543b8c4fb6b0262e9a73abae3d.xml#id-fa888b543b8c4fb6b0262e9a73abae3d"/>
      </sourceConnections>
      <sourceConnections
          xsi:type="archimate:DiagramModelArchimateConnection"
          id="id-2374f520cd8049f3b6f2ac418e58d83e"
          font="1|Segoe UI|9.0|0|WINDOWS|1|-15|0|0|0|0|0|0|0|0|3|2|1|34|Segoe UI"
          source="id-7344897a0ba74cd8b5c0f574706ad950"
          target="id-3480494b7dea488088ffee3a62a4398d">
        <archimateRelationship
            xsi:type="archimate:AggregationRelationship"
            href="AggregationRelationship_id-b3b62aa8a6e14b148a003089f5abff7a.xml#id-b3b62aa8a6e14b148a003089f5abff7a"/>
      </sourceConnections>
      <sourceConnections
          xsi:type="archimate:DiagramModelArchimateConnection"
          id="id-b41f837651f14f72801faedb012ed78f"
          font="1|Segoe UI|9.0|0|WINDOWS|1|-15|0|0|0|0|0|0|0|0|3|2|1|34|Segoe UI"
          source="id-7344897a0ba74cd8b5c0f574706ad950"
          target="id-35d420442cd9493e8269c5550c3a12ba">
        <archimateRelationship
            xsi:type="archimate:AggregationRelationship"
            href="AggregationRelationship_id-0a82e76a38ec480da46c746630aa8c13.xml#id-0a82e76a38ec480da46c746630aa8c13"/>
      </sourceConnections>
      <bounds
          x="379"
          y="26"
          width="347"
          height="213"/>
      <children
          xsi:type="archimate:DiagramModelArchimateObject"
          id="id-35d420442cd9493e8269c5550c3a12ba"
          targetConnections="id-b41f837651f14f72801faedb012ed78f"
          font="1|Segoe UI|9.0|0|WINDOWS|1|0|0|0|0|0|0|0|0|1|0|0|0|0|Segoe UI"
          fontColor="#000000"
          lineColor="#000000"
          fillColor="#ffffcc">
        <bounds
            x="15"
            y="87"
            width="147"
            height="53"/>
        <archimateElement
            xsi:type="archimate:BusinessFunction"
            href="BusinessFunction_id-8e9b96c786e540eba15fdbfb1a3d111f.xml#id-8e9b96c786e540eba15fdbfb1a3d111f"/>
      </children>
      <children
          xsi:type="archimate:DiagramModelArchimateObject"
          id="id-90391b9c874149a39d6aa6ad43cbf1be"
          targetConnections="id-9154b013c96a4d908ea5212fd5b4557f"
          font="1|Segoe UI|9.0|0|WINDOWS|1|0|0|0|0|0|0|0|0|1|0|0|0|0|Segoe UI"
          fontColor="#000000"
          lineColor="#000000"
          fillColor="#ffffcc">
        <bounds
            x="15"
            y="147"
            width="147"
            height="53"/>
        <archimateElement
            xsi:type="archimate:BusinessFunction"
            href="BusinessFunction_id-8dc98e91f87b4fa998ca6f32b5522866.xml#id-8dc98e91f87b4fa998ca6f32b5522866"/>
      </children>
      <children
          xsi:type="archimate:DiagramModelArchimateObject"
          id="id-961a8f3bdae84b9298c092753c2062b5"
          targetConnections="id-b7c59e36e5fe4c58806d3b5156dc74f1"
          font="1|Segoe UI|9.0|0|WINDOWS|1|0|0|0|0|0|0|0|0|1|0|0|0|0|Segoe UI"
          fontColor="#000000"
          lineColor="#000000"
          fillColor="#ffffcc">
        <bounds
            x="15"
            y="27"
            width="147"
            height="53"/>
        <archimateElement
            xsi:type="archimate:BusinessFunction"
            href="BusinessFunction_id-cc5ba856569949f3ac58edce78495b9b.xml#id-cc5ba856569949f3ac58edce78495b9b"/>
      </children>
      <children
          xsi:type="archimate:DiagramModelArchimateObject"
          id="id-efabed6086994fe28a676db36d924968"
          targetConnections="id-67d1cc32146d4f9094a7be9f589651fa"
          font="1|Segoe UI|9.0|0|WINDOWS|1|0|0|0|0|0|0|0|0|1|0|0|0|0|Segoe UI"
          fontColor="#000000"
          lineColor="#000000"
          fillColor="#ffffcc">
        <bounds
            x="174"
            y="87"
            width="147"
            height="53"/>
        <archimateElement
            xsi:type="archimate:BusinessFunction"
            href="BusinessFunction_id-daacf79f26194123a881d68c49a669ce.xml#id-daacf79f26194123a881d68c49a669ce"/>
      </children>
      <children
          xsi:type="archimate:DiagramModelArchimateObject"
          id="id-3480494b7dea488088ffee3a62a4398d"
          targetConnections="id-2374f520cd8049f3b6f2ac418e58d83e"
          font="1|Segoe UI|9.0|0|WINDOWS|1|0|0|0|0|0|0|0|0|1|0|0|0|0|Segoe UI"
          fontColor="#000000"
          lineColor="#000000"
          fillColor="#ffffcc">
        <bounds
            x="174"
            y="27"
            width="147"
            height="53"/>
        <archimateElement
            xsi:type="archimate:BusinessFunction"
            href="BusinessFunction_id-9cb46c5cba0a422e9420b5a2a7e52721.xml#id-9cb46c5cba0a422e9420b5a2a7e52721"/>
      </children>
      <archimateElement
          xsi:type="archimate:BusinessFunction"
          href="BusinessFunction_id-7ccad4a85b0440228c6ce9a05ce90edd.xml#id-7ccad4a85b0440228c6ce9a05ce90edd"/>
    </children>
    <children
        xsi:type="archimate:DiagramModelArchimateObject"
        id="id-396b786ab31e4b04961660968f880d19"
        targetConnections="id-df16f713bbc845ebb719fe4d70cb83e7"
        font="1|Segoe UI|9.0|0|WINDOWS|1|0|0|0|0|0|0|0|0|1|0|0|0|0|Segoe UI"
        fontColor="#000000"
        lineColor="#000000"
        fillColor="#fff8b7">
      <sourceConnections
          xsi:type="archimate:DiagramModelArchimateConnection"
          id="id-4bf4ea22c0ab4669a94f1e5e814744ea"
          font="1|Segoe UI|9.0|0|WINDOWS|1|-15|0|0|0|0|0|0|0|0|3|2|1|34|Segoe UI"
          source="id-396b786ab31e4b04961660968f880d19"
          target="id-d80c3eee03834006be2304407219d957">
        <archimateRelationship
            xsi:type="archimate:AggregationRelationship"
            href="AggregationRelationship_id-af1cddf1a89140e9b86c4f6974ca04a3.xml#id-af1cddf1a89140e9b86c4f6974ca04a3"/>
      </sourceConnections>
      <sourceConnections
          xsi:type="archimate:DiagramModelArchimateConnection"
          id="id-33b45a8a8ad84621ad3da7ed4fcfaa3e"
          font="1|Segoe UI|9.0|0|WINDOWS|1|-15|0|0|0|0|0|0|0|0|3|2|1|34|Segoe UI"
          source="id-396b786ab31e4b04961660968f880d19"
          target="id-abf29cb7637d4ddeb5f33c8817bdb5e3">
        <archimateRelationship
            xsi:type="archimate:AggregationRelationship"
            href="AggregationRelationship_id-a1aaeb371eb2429486b9d321ceab27d0.xml#id-a1aaeb371eb2429486b9d321ceab27d0"/>
      </sourceConnections>
      <sourceConnections
          xsi:type="archimate:DiagramModelArchimateConnection"
          id="id-b973848ba4c7486f9f1756635d9a0f6f"
          font="1|Segoe UI|9.0|0|WINDOWS|1|-15|0|0|0|0|0|0|0|0|3|2|1|34|Segoe UI"
          source="id-396b786ab31e4b04961660968f880d19"
          target="id-5c2d98bedc7748d09ea47f5c1ff8fc9b">
        <archimateRelationship
            xsi:type="archimate:AggregationRelationship"
            href="AggregationRelationship_id-f13e12c414914d4aa6405299e0264231.xml#id-f13e12c414914d4aa6405299e0264231"/>
      </sourceConnections>
      <sourceConnections
          xsi:type="archimate:DiagramModelArchimateConnection"
          id="id-931508fe1e874f0787534580dceb8b36"
          font="1|Segoe UI|9.0|0|WINDOWS|1|-15|0|0|0|0|0|0|0|0|3|2|1|34|Segoe UI"
          source="id-396b786ab31e4b04961660968f880d19"
          target="id-624b828d4cbc4a34b26ca221b9dfdbef">
        <archimateRelationship
            xsi:type="archimate:AggregationRelationship"
            href="AggregationRelationship_id-d95ec6f509d44dc6aa80f8133a1f5372.xml#id-d95ec6f509d44dc6aa80f8133a1f5372"/>
      </sourceConnections>
      <sourceConnections
          xsi:type="archimate:DiagramModelArchimateConnection"
          id="id-a48b164400ca481a9e3c31d59c7b1712"
          font="1|Segoe UI|9.0|0|WINDOWS|1|-15|0|0|0|0|0|0|0|0|3|2|1|34|Segoe UI"
          source="id-396b786ab31e4b04961660968f880d19"
          target="id-2d6c5ac62fe94255a8ffecd7cea9f83e">
        <archimateRelationship
            xsi:type="archimate:AggregationRelationship"
            href="AggregationRelationship_id-889e7dba749c479ca19ff55c5e15011c.xml#id-889e7dba749c479ca19ff55c5e15011c"/>
      </sourceConnections>
      <bounds
          x="1112"
          y="26"
          width="347"
          height="213"/>
      <children
          xsi:type="archimate:DiagramModelArchimateObject"
          id="id-2d6c5ac62fe94255a8ffecd7cea9f83e"
          targetConnections="id-a48b164400ca481a9e3c31d59c7b1712"
          font="1|Segoe UI|9.0|0|WINDOWS|1|0|0|0|0|0|0|0|0|1|0|0|0|0|Segoe UI"
          fontColor="#000000"
          lineColor="#000000"
          fillColor="#ffffcc">
        <bounds
            x="181"
            y="27"
            width="147"
            height="53"/>
        <archimateElement
            xsi:type="archimate:BusinessFunction"
            href="BusinessFunction_id-e7a5e984710b48fc8262b6dcbdc8d138.xml#id-e7a5e984710b48fc8262b6dcbdc8d138"/>
      </children>
      <children
          xsi:type="archimate:DiagramModelArchimateObject"
          id="id-d80c3eee03834006be2304407219d957"
          targetConnections="id-4bf4ea22c0ab4669a94f1e5e814744ea"
          font="1|Segoe UI|9.0|0|WINDOWS|1|0|0|0|0|0|0|0|0|1|0|0|0|0|Segoe UI"
          fontColor="#000000"
          lineColor="#000000"
          fillColor="#ffffcc">
        <bounds
            x="21"
            y="27"
            width="147"
            height="53"/>
        <archimateElement
            xsi:type="archimate:BusinessFunction"
            href="BusinessFunction_id-ac5f571766d44ba5850b28cd2b5bc488.xml#id-ac5f571766d44ba5850b28cd2b5bc488"/>
      </children>
      <children
          xsi:type="archimate:DiagramModelArchimateObject"
          id="id-abf29cb7637d4ddeb5f33c8817bdb5e3"
          targetConnections="id-33b45a8a8ad84621ad3da7ed4fcfaa3e"
          font="1|Segoe UI|9.0|0|WINDOWS|1|0|0|0|0|0|0|0|0|1|0|0|0|0|Segoe UI"
          fontColor="#000000"
          lineColor="#000000"
          fillColor="#ffffcc">
        <bounds
            x="21"
            y="87"
            width="147"
            height="53"/>
        <archimateElement
            xsi:type="archimate:BusinessFunction"
            href="BusinessFunction_id-3b2741b1e30c44bd96828d9af55a5e73.xml#id-3b2741b1e30c44bd96828d9af55a5e73"/>
      </children>
      <children
          xsi:type="archimate:DiagramModelArchimateObject"
          id="id-5c2d98bedc7748d09ea47f5c1ff8fc9b"
          targetConnections="id-b973848ba4c7486f9f1756635d9a0f6f"
          font="1|Segoe UI|9.0|0|WINDOWS|1|0|0|0|0|0|0|0|0|1|0|0|0|0|Segoe UI"
          fontColor="#000000"
          lineColor="#000000"
          fillColor="#ffffcc">
        <bounds
            x="21"
            y="147"
            width="147"
            height="53"/>
        <archimateElement
            xsi:type="archimate:BusinessFunction"
            href="BusinessFunction_id-e9131e6143cb431491ca02a0b065360c.xml#id-e9131e6143cb431491ca02a0b065360c"/>
      </children>
      <children
          xsi:type="archimate:DiagramModelArchimateObject"
          id="id-624b828d4cbc4a34b26ca221b9dfdbef"
          targetConnections="id-931508fe1e874f0787534580dceb8b36"
          font="1|Segoe UI|9.0|0|WINDOWS|1|0|0|0|0|0|0|0|0|1|0|0|0|0|Segoe UI"
          fontColor="#000000"
          lineColor="#000000"
          fillColor="#ffffcc">
        <bounds
            x="181"
            y="87"
            width="147"
            height="53"/>
        <archimateElement
            xsi:type="archimate:BusinessFunction"
            href="BusinessFunction_id-b5af4fa3c1964b18a55fcf6bde662c18.xml#id-b5af4fa3c1964b18a55fcf6bde662c18"/>
      </children>
      <archimateElement
          xsi:type="archimate:BusinessFunction"
          href="BusinessFunction_id-142056dc4946492db6ad7956029b449a.xml#id-142056dc4946492db6ad7956029b449a"/>
    </children>
    <children
        xsi:type="archimate:DiagramModelArchimateObject"
        id="id-7982cc1be95040e9bfe2a2c2f222a42c"
        targetConnections="id-aa37102eabfb44c6b860752b5f7c6442"
        font="1|Segoe UI|9.0|0|WINDOWS|1|0|0|0|0|0|0|0|0|1|0|0|0|0|Segoe UI"
        fontColor="#000000"
        lineColor="#000000"
        fillColor="#fff8b7">
      <sourceConnections
          xsi:type="archimate:DiagramModelArchimateConnection"
          id="id-cd708c0446254d93811511bf7751e974"
          font="1|Segoe UI|9.0|0|WINDOWS|1|-15|0|0|0|0|0|0|0|0|3|2|1|34|Segoe UI"
          source="id-7982cc1be95040e9bfe2a2c2f222a42c"
          target="id-09ebdbd70dba479b905778c2728c13a8">
        <archimateRelationship
            xsi:type="archimate:AggregationRelationship"
            href="AggregationRelationship_id-14dee751aceb48fb84bcb1ed4e79c0fc.xml#id-14dee751aceb48fb84bcb1ed4e79c0fc"/>
      </sourceConnections>
      <sourceConnections
          xsi:type="archimate:DiagramModelArchimateConnection"
          id="id-3bdbb5c586e348ec939d6a168fa7b07b"
          font="1|Segoe UI|9.0|0|WINDOWS|1|-15|0|0|0|0|0|0|0|0|3|2|1|34|Segoe UI"
          source="id-7982cc1be95040e9bfe2a2c2f222a42c"
          target="id-98e86fb20697479fbebee93a1d7849d3">
        <archimateRelationship
            xsi:type="archimate:AggregationRelationship"
            href="AggregationRelationship_id-acadb44397a84b0c9e493a7ac37914f9.xml#id-acadb44397a84b0c9e493a7ac37914f9"/>
      </sourceConnections>
      <sourceConnections
          xsi:type="archimate:DiagramModelArchimateConnection"
          id="id-9fa20ddcee9b4f0b80b7a2de8d865aa9"
          font="1|Segoe UI|9.0|0|WINDOWS|1|-15|0|0|0|0|0|0|0|0|3|2|1|34|Segoe UI"
          source="id-7982cc1be95040e9bfe2a2c2f222a42c"
          target="id-3020f3423d8644ccac42fffbb64f7655">
        <archimateRelationship
            xsi:type="archimate:AggregationRelationship"
            href="AggregationRelationship_id-959be58d4f8046a7aaffa7f1a92732b6.xml#id-959be58d4f8046a7aaffa7f1a92732b6"/>
      </sourceConnections>
      <sourceConnections
          xsi:type="archimate:DiagramModelArchimateConnection"
          id="id-92c13a0f7b39405284aa0c34e067ebf4"
          font="1|Segoe UI|9.0|0|WINDOWS|1|-15|0|0|0|0|0|0|0|0|3|2|1|34|Segoe UI"
          source="id-7982cc1be95040e9bfe2a2c2f222a42c"
          target="id-4b442a14a96d4088bcacce528e8780b4">
        <archimateRelationship
            xsi:type="archimate:AggregationRelationship"
            href="AggregationRelationship_id-fcf95b66cb2041558f86a209b6156727.xml#id-fcf95b66cb2041558f86a209b6156727"/>
      </sourceConnections>
      <bounds
          x="746"
          y="26"
          width="347"
          height="213"/>
      <children
          xsi:type="archimate:DiagramModelArchimateObject"
          id="id-4b442a14a96d4088bcacce528e8780b4"
          targetConnections="id-92c13a0f7b39405284aa0c34e067ebf4"
          font="1|Segoe UI|9.0|0|WINDOWS|1|0|0|0|0|0|0|0|0|1|0|0|0|0|Segoe UI"
          fontColor="#000000"
          lineColor="#000000"
          fillColor="#ffffcc">
        <bounds
            x="180"
            y="87"
            width="147"
            height="53"/>
        <archimateElement
            xsi:type="archimate:BusinessFunction"
            href="BusinessFunction_id-f298d5a28f634d3d82354b952fb7b117.xml#id-f298d5a28f634d3d82354b952fb7b117"/>
      </children>
      <children
          xsi:type="archimate:DiagramModelArchimateObject"
          id="id-3020f3423d8644ccac42fffbb64f7655"
          targetConnections="id-9fa20ddcee9b4f0b80b7a2de8d865aa9"
          font="1|Segoe UI|9.0|0|WINDOWS|1|0|0|0|0|0|0|0|0|1|0|0|0|0|Segoe UI"
          fontColor="#000000"
          lineColor="#000000"
          fillColor="#ffffcc">
        <bounds
            x="20"
            y="27"
            width="147"
            height="53"/>
        <archimateElement
            xsi:type="archimate:BusinessFunction"
            href="BusinessFunction_id-82ec634cccf541e3b2ce1878aeef71ad.xml#id-82ec634cccf541e3b2ce1878aeef71ad"/>
      </children>
      <children
          xsi:type="archimate:DiagramModelArchimateObject"
          id="id-98e86fb20697479fbebee93a1d7849d3"
          targetConnections="id-3bdbb5c586e348ec939d6a168fa7b07b"
          font="1|Segoe UI|9.0|0|WINDOWS|1|0|0|0|0|0|0|0|0|1|0|0|0|0|Segoe UI"
          fontColor="#000000"
          lineColor="#000000"
          fillColor="#ffffcc">
        <bounds
            x="20"
            y="87"
            width="147"
            height="53"/>
        <archimateElement
            xsi:type="archimate:BusinessFunction"
            href="BusinessFunction_id-b37d1bb6fb8e4c718eb0ed096f03e25a.xml#id-b37d1bb6fb8e4c718eb0ed096f03e25a"/>
      </children>
      <children
          xsi:type="archimate:DiagramModelArchimateObject"
          id="id-09ebdbd70dba479b905778c2728c13a8"
          targetConnections="id-cd708c0446254d93811511bf7751e974"
          font="1|Segoe UI|9.0|0|WINDOWS|1|0|0|0|0|0|0|0|0|1|0|0|0|0|Segoe UI"
          fontColor="#000000"
          lineColor="#000000"
          fillColor="#ffffcc">
        <bounds
            x="180"
            y="27"
            width="147"
            height="53"/>
        <archimateElement
            xsi:type="archimate:BusinessFunction"
            href="BusinessFunction_id-3ceb967d97544694b08080d5ae26910e.xml#id-3ceb967d97544694b08080d5ae26910e"/>
      </children>
      <archimateElement
          xsi:type="archimate:BusinessFunction"
          href="BusinessFunction_id-0afc5ca3bdfa48d8b2670c59cbfcdba3.xml#id-0afc5ca3bdfa48d8b2670c59cbfcdba3"/>
    </children>
    <archimateElement
        xsi:type="archimate:BusinessFunction"
        href="BusinessFunction_id-c693b7b344cd442eb71185a4fbcc6b9b.xml#id-c693b7b344cd442eb71185a4fbcc6b9b"/>
  </children>
  <children
      xsi:type="archimate:DiagramModelArchimateObject"
      id="id-bc156e4df8af4ffcbfffb7b9ebd9c8fa"
      font="1|Segoe UI|10.0|0|WINDOWS|1|0|0|0|0|0|0|0|0|1|0|0|0|0|Segoe UI"
      fontColor="#000000"
      lineColor="#000000"
      fillColor="#fff29b">
    <sourceConnections
        xsi:type="archimate:DiagramModelArchimateConnection"
        id="id-12ac86eeda984d9f957ff3764eb242fa"
        font="1|Segoe UI|9.0|0|WINDOWS|1|-15|0|0|0|0|0|0|0|0|3|2|1|34|Segoe UI"
        source="id-bc156e4df8af4ffcbfffb7b9ebd9c8fa"
        target="id-19bf43922d4a4e3ebe2adb0e3f91db11">
      <archimateRelationship
          xsi:type="archimate:AggregationRelationship"
          href="AggregationRelationship_id-48c71c7bd1554a3fa179121f1c25eac2.xml#id-48c71c7bd1554a3fa179121f1c25eac2"/>
    </sourceConnections>
    <sourceConnections
        xsi:type="archimate:DiagramModelArchimateConnection"
        id="id-52a154ccb9b941c6be10c5a38792cdb5"
        font="1|Segoe UI|9.0|0|WINDOWS|1|-15|0|0|0|0|0|0|0|0|3|2|1|34|Segoe UI"
        source="id-bc156e4df8af4ffcbfffb7b9ebd9c8fa"
        target="id-abac81e3921a48e6927747f1e5c12b6c">
      <archimateRelationship
          xsi:type="archimate:AggregationRelationship"
          href="AggregationRelationship_id-0b6a3524294c45ed818814da20e1b2b3.xml#id-0b6a3524294c45ed818814da20e1b2b3"/>
    </sourceConnections>
    <sourceConnections
        xsi:type="archimate:DiagramModelArchimateConnection"
        id="id-2b2d5f6990ee44bd9540b93c3f3df36a"
        font="1|Segoe UI|9.0|0|WINDOWS|1|-15|0|0|0|0|0|0|0|0|3|2|1|34|Segoe UI"
        source="id-bc156e4df8af4ffcbfffb7b9ebd9c8fa"
        target="id-c8924097c1d941b28a14bd749132626b">
      <archimateRelationship
          xsi:type="archimate:AggregationRelationship"
          href="AggregationRelationship_id-8cf8f587fe8d4ca7889ed8d6b3354965.xml#id-8cf8f587fe8d4ca7889ed8d6b3354965"/>
    </sourceConnections>
    <sourceConnections
        xsi:type="archimate:DiagramModelArchimateConnection"
        id="id-53f6168b111f4878b1a9ee7ad817864c"
        font="1|Segoe UI|9.0|0|WINDOWS|1|-15|0|0|0|0|0|0|0|0|3|2|1|34|Segoe UI"
        source="id-bc156e4df8af4ffcbfffb7b9ebd9c8fa"
        target="id-198c7d3f782a4ee6a390ae53925338fd">
      <archimateRelationship
          xsi:type="archimate:AggregationRelationship"
          href="AggregationRelationship_id-f46b1e0bb6a945a0972caadf9ce5ff30.xml#id-f46b1e0bb6a945a0972caadf9ce5ff30"/>
    </sourceConnections>
    <bounds
        x="26"
        y="368"
        width="1480"
        height="87"/>
    <children
        xsi:type="archimate:DiagramModelArchimateObject"
        id="id-19bf43922d4a4e3ebe2adb0e3f91db11"
        targetConnections="id-12ac86eeda984d9f957ff3764eb242fa"
        font="1|Segoe UI|9.0|0|WINDOWS|1|0|0|0|0|0|0|0|0|1|0|0|0|0|Segoe UI"
        fontColor="#000000"
        lineColor="#000000"
        fillColor="#ffffcc">
      <bounds
          x="1246"
          y="20"
          width="193"
          height="53"/>
      <archimateElement
          xsi:type="archimate:BusinessFunction"
          href="BusinessFunction_id-08031425b25c4bfe8bccb975dae05776.xml#id-08031425b25c4bfe8bccb975dae05776"/>
    </children>
    <children
        xsi:type="archimate:DiagramModelArchimateObject"
        id="id-abac81e3921a48e6927747f1e5c12b6c"
        targetConnections="id-52a154ccb9b941c6be10c5a38792cdb5"
        font="1|Segoe UI|9.0|0|WINDOWS|1|0|0|0|0|0|0|0|0|1|0|0|0|0|Segoe UI"
        fontColor="#000000"
        lineColor="#000000"
        fillColor="#ffffcc">
      <bounds
          x="761"
          y="21"
          width="193"
          height="53"/>
      <archimateElement
          xsi:type="archimate:BusinessFunction"
          href="BusinessFunction_id-220772ee128842e180a7ba8a90468713.xml#id-220772ee128842e180a7ba8a90468713"/>
    </children>
    <children
        xsi:type="archimate:DiagramModelArchimateObject"
        id="id-198c7d3f782a4ee6a390ae53925338fd"
        targetConnections="id-53f6168b111f4878b1a9ee7ad817864c"
        font="1|Segoe UI|9.0|0|WINDOWS|1|0|0|0|0|0|0|0|0|1|0|0|0|0|Segoe UI"
        fontColor="#000000"
        lineColor="#000000"
        fillColor="#ffffcc">
      <bounds
          x="518"
          y="21"
          width="193"
          height="53"/>
      <archimateElement
          xsi:type="archimate:BusinessFunction"
          href="BusinessFunction_id-a450e41f62c14bb680b4f84e0a923a43.xml#id-a450e41f62c14bb680b4f84e0a923a43"/>
    </children>
    <children
        xsi:type="archimate:DiagramModelArchimateObject"
        id="id-c8924097c1d941b28a14bd749132626b"
        targetConnections="id-2b2d5f6990ee44bd9540b93c3f3df36a"
        font="1|Segoe UI|9.0|0|WINDOWS|1|0|0|0|0|0|0|0|0|1|0|0|0|0|Segoe UI"
        fontColor="#000000"
        lineColor="#000000"
        fillColor="#e5c1a7">
      <bounds
          x="33"
          y="21"
          width="193"
          height="53"/>
      <archimateElement
          xsi:type="archimate:BusinessFunction"
          href="BusinessFunction_id-3a0ab7f804874fcdb63e96b7a57f1798.xml#id-3a0ab7f804874fcdb63e96b7a57f1798"/>
    </children>
    <archimateElement
        xsi:type="archimate:BusinessFunction"
        href="BusinessFunction_id-78b8a4b82b49409084c2af8eb2f7c7c4.xml#id-78b8a4b82b49409084c2af8eb2f7c7c4"/>
  </children>
  <children
      xsi:type="archimate:DiagramModelArchimateObject"
      id="id-8c4987284baf488f92fd95de8eed65f0"
      font="1|Segoe UI|10.0|0|WINDOWS|1|0|0|0|0|0|0|0|0|1|0|0|0|0|Segoe UI"
      fontColor="#000000"
      lineColor="#000000"
      fillColor="#fff29b">
    <sourceConnections
        xsi:type="archimate:DiagramModelArchimateConnection"
        id="id-71cfc8a850c7408d80854de582dc8455"
        font="1|Segoe UI|9.0|0|WINDOWS|1|-15|0|0|0|0|0|0|0|0|3|2|1|34|Segoe UI"
        source="id-8c4987284baf488f92fd95de8eed65f0"
        target="id-6283382637a1433081840f6230d67fdb">
      <archimateRelationship
          xsi:type="archimate:AggregationRelationship"
          href="AggregationRelationship_id-95bce3213b5b4774b8a266f931563730.xml#id-95bce3213b5b4774b8a266f931563730"/>
    </sourceConnections>
    <sourceConnections
        xsi:type="archimate:DiagramModelArchimateConnection"
        id="id-701c8669ef5e455f9b73e5985c9de93d"
        font="1|Segoe UI|9.0|0|WINDOWS|1|-15|0|0|0|0|0|0|0|0|3|2|1|34|Segoe UI"
        source="id-8c4987284baf488f92fd95de8eed65f0"
        target="id-96161b5ccb2441c9be187580c8f0a560">
      <archimateRelationship
          xsi:type="archimate:AggregationRelationship"
          href="AggregationRelationship_id-7f9f9e632d23433499605845874df372.xml#id-7f9f9e632d23433499605845874df372"/>
    </sourceConnections>
    <sourceConnections
        xsi:type="archimate:DiagramModelArchimateConnection"
        id="id-b235bd56f6fd4fef8af06a08c1ab24f1"
        font="1|Segoe UI|9.0|0|WINDOWS|1|-15|0|0|0|0|0|0|0|0|3|2|1|34|Segoe UI"
        source="id-8c4987284baf488f92fd95de8eed65f0"
        target="id-71838959445f4dbc846911c2ff1ad964">
      <archimateRelationship
          xsi:type="archimate:AggregationRelationship"
          href="AggregationRelationship_id-1db4fe8a6ef44b5caed693c4d90d7890.xml#id-1db4fe8a6ef44b5caed693c4d90d7890"/>
    </sourceConnections>
    <sourceConnections
        xsi:type="archimate:DiagramModelArchimateConnection"
        id="id-63c7510c990147538484eb55674e2ae8"
        font="1|Segoe UI|9.0|0|WINDOWS|1|-15|0|0|0|0|0|0|0|0|3|2|1|34|Segoe UI"
        source="id-8c4987284baf488f92fd95de8eed65f0"
        target="id-9cd070b7610a44e2b0ec490a405c310e">
      <archimateRelationship
          xsi:type="archimate:AggregationRelationship"
          href="AggregationRelationship_id-8c72391091fd4dff9d4f0da1e8e48a17.xml#id-8c72391091fd4dff9d4f0da1e8e48a17"/>
    </sourceConnections>
    <sourceConnections
        xsi:type="archimate:DiagramModelArchimateConnection"
        id="id-49156268e1e648988aa1bd4d465a4cb0"
        font="1|Segoe UI|9.0|0|WINDOWS|1|-15|0|0|0|0|0|0|0|0|3|2|1|34|Segoe UI"
        source="id-8c4987284baf488f92fd95de8eed65f0"
        target="id-494cc09d6b444ce1855b75b69fccbdd4">
      <archimateRelationship
          xsi:type="archimate:AggregationRelationship"
          href="AggregationRelationship_id-68bb65e0b08047898724ca715edf2c0f.xml#id-68bb65e0b08047898724ca715edf2c0f"/>
    </sourceConnections>
    <sourceConnections
        xsi:type="archimate:DiagramModelArchimateConnection"
        id="id-b868daf9db80445aa9d70f333bdf70ba"
        font="1|Segoe UI|9.0|0|WINDOWS|1|-15|0|0|0|0|0|0|0|0|3|2|1|34|Segoe UI"
        source="id-8c4987284baf488f92fd95de8eed65f0"
        target="id-b670339d465f4a38821b7ac0c4a8b71b">
      <archimateRelationship
          xsi:type="archimate:AggregationRelationship"
          href="AggregationRelationship_id-b66f83ec0dc3471c990a88139393f20d.xml#id-b66f83ec0dc3471c990a88139393f20d"/>
    </sourceConnections>
    <bounds
        x="26"
        y="275"
        width="1480"
        height="87"/>
    <children
        xsi:type="archimate:DiagramModelArchimateObject"
        id="id-b670339d465f4a38821b7ac0c4a8b71b"
        targetConnections="id-b868daf9db80445aa9d70f333bdf70ba"
        font="1|Segoe UI|9.0|0|WINDOWS|1|0|0|0|0|0|0|0|0|1|0|0|0|0|Segoe UI"
        fontColor="#000000"
        lineColor="#000000"
        fillColor="#ffffcc">
      <bounds
          x="1246"
          y="19"
          width="193"
          height="53"/>
      <archimateElement
          xsi:type="archimate:BusinessFunction"
          href="BusinessFunction_id-24ae11afdfae4cc7b2eac22b03090ea5.xml#id-24ae11afdfae4cc7b2eac22b03090ea5"/>
    </children>
    <children
        xsi:type="archimate:DiagramModelArchimateObject"
        id="id-71838959445f4dbc846911c2ff1ad964"
        targetConnections="id-b235bd56f6fd4fef8af06a08c1ab24f1"
        font="1|Segoe UI|9.0|0|WINDOWS|1|0|0|0|0|0|0|0|0|1|0|0|0|0|Segoe UI"
        fontColor="#000000"
        lineColor="#000000"
        fillColor="#ffffcc">
      <bounds
          x="1004"
          y="20"
          width="193"
          height="53"/>
      <archimateElement
          xsi:type="archimate:BusinessFunction"
          href="BusinessFunction_id-62dd4cc60ed341f4994a71c7fdef69dd.xml#id-62dd4cc60ed341f4994a71c7fdef69dd"/>
    </children>
    <children
        xsi:type="archimate:DiagramModelArchimateObject"
        id="id-96161b5ccb2441c9be187580c8f0a560"
        targetConnections="id-701c8669ef5e455f9b73e5985c9de93d"
        font="1|Segoe UI|9.0|0|WINDOWS|1|0|0|0|0|0|0|0|0|1|0|0|0|0|Segoe UI"
        fontColor="#000000"
        lineColor="#000000"
        fillColor="#ffffcc">
      <bounds
          x="761"
          y="20"
          width="193"
          height="53"/>
      <archimateElement
          xsi:type="archimate:BusinessFunction"
          href="BusinessFunction_id-4dcc98432b7342c585abc3be5e626688.xml#id-4dcc98432b7342c585abc3be5e626688"/>
    </children>
    <children
        xsi:type="archimate:DiagramModelArchimateObject"
        id="id-6283382637a1433081840f6230d67fdb"
        targetConnections="id-71cfc8a850c7408d80854de582dc8455"
        font="1|Segoe UI|9.0|0|WINDOWS|1|0|0|0|0|0|0|0|0|1|0|0|0|0|Segoe UI"
        fontColor="#000000"
        lineColor="#000000"
        fillColor="#ffffcc">
      <bounds
          x="518"
          y="20"
          width="193"
          height="53"/>
      <archimateElement
          xsi:type="archimate:BusinessFunction"
          href="BusinessFunction_id-dd2bc7638bdf439183a8fef7b510f476.xml#id-dd2bc7638bdf439183a8fef7b510f476"/>
    </children>
    <children
        xsi:type="archimate:DiagramModelArchimateObject"
        id="id-494cc09d6b444ce1855b75b69fccbdd4"
        targetConnections="id-49156268e1e648988aa1bd4d465a4cb0"
        font="1|Segoe UI|9.0|0|WINDOWS|1|0|0|0|0|0|0|0|0|1|0|0|0|0|Segoe UI"
        fontColor="#000000"
        lineColor="#000000"
        fillColor="#e4c1a7">
      <bounds
          x="276"
          y="20"
          width="193"
          height="53"/>
      <archimateElement
          xsi:type="archimate:BusinessFunction"
          href="BusinessFunction_id-111885ba6f294ffeb7bf42e2b3ef2b8c.xml#id-111885ba6f294ffeb7bf42e2b3ef2b8c"/>
    </children>
    <children
        xsi:type="archimate:DiagramModelArchimateObject"
        id="id-9cd070b7610a44e2b0ec490a405c310e"
        targetConnections="id-63c7510c990147538484eb55674e2ae8"
        font="1|Segoe UI|9.0|0|WINDOWS|1|0|0|0|0|0|0|0|0|1|0|0|0|0|Segoe UI"
        fontColor="#000000"
        lineColor="#000000"
        fillColor="#ffffcc">
      <bounds
          x="33"
          y="20"
          width="193"
          height="53"/>
      <archimateElement
          xsi:type="archimate:BusinessFunction"
          href="BusinessFunction_id-4e7d41de8dfb4c72b2df01298d78ed8c.xml#id-4e7d41de8dfb4c72b2df01298d78ed8c"/>
    </children>
    <archimateElement
        xsi:type="archimate:BusinessFunction"
        href="BusinessFunction_id-5eabfe10b5124f469f5d56ca838486ed.xml#id-5eabfe10b5124f469f5d56ca838486ed"/>
  </children>
  <children
      xsi:type="archimate:DiagramModelNote"
      id="id-ae4f489f2f364acba9cdcd65bc4c75c5"
      font="1|arial|12.0|0|WINDOWS|1|0|0|0|0|0|0|0|0|1|0|0|0|0|arial"
      fontColor="#000000"
      lineColor="#000000"
      textAlignment="1"
      fillColor="#ffffff"
      content="Ondersteunende functies">
    <bounds
        x="12"
        y="941"
        width="1507"
        height="193"/>
  </children>
  <children
      xsi:type="archimate:DiagramModelArchimateObject"
      id="id-f8ba8ff5d13641288d3c54dd9935a79b"
      font="1|Segoe UI|10.0|0|WINDOWS|1|0|0|0|0|0|0|0|0|1|0|0|0|0|Segoe UI"
      fontColor="#000000"
      lineColor="#000000"
      fillColor="#fff29b">
    <sourceConnections
        xsi:type="archimate:DiagramModelArchimateConnection"
        id="id-a67d3eef7f2b4bf1a0ff2f4c5019ea5f"
        font="1|Segoe UI|9.0|0|WINDOWS|1|-15|0|0|0|0|0|0|0|0|3|2|1|34|Segoe UI"
        source="id-f8ba8ff5d13641288d3c54dd9935a79b"
        target="id-518b239032774056a23e0722b2841dcb">
      <archimateRelationship
          xsi:type="archimate:AggregationRelationship"
          href="AggregationRelationship_id-f5c7f30106ec4a7b977ce4acf9853e31.xml#id-f5c7f30106ec4a7b977ce4acf9853e31"/>
    </sourceConnections>
    <sourceConnections
        xsi:type="archimate:DiagramModelArchimateConnection"
        id="id-3414b24936784ad4b9e2b24319ebc11d"
        font="1|Segoe UI|9.0|0|WINDOWS|1|-15|0|0|0|0|0|0|0|0|3|2|1|34|Segoe UI"
        source="id-f8ba8ff5d13641288d3c54dd9935a79b"
        target="id-36e2f48e055c43dcaf43dfa9e88cbf3d">
      <archimateRelationship
          xsi:type="archimate:AggregationRelationship"
          href="AggregationRelationship_id-22f25f93b3474bfd9f2068c5519eec72.xml#id-22f25f93b3474bfd9f2068c5519eec72"/>
    </sourceConnections>
    <sourceConnections
        xsi:type="archimate:DiagramModelArchimateConnection"
        id="id-1238e56c5da243239a5934cfd733faf7"
        font="1|Segoe UI|9.0|0|WINDOWS|1|-15|0|0|0|0|0|0|0|0|3|2|1|34|Segoe UI"
        source="id-f8ba8ff5d13641288d3c54dd9935a79b"
        target="id-062b9dee702a443ba9c84ef1572d09b2">
      <archimateRelationship
          xsi:type="archimate:AggregationRelationship"
          href="AggregationRelationship_id-a401626b1b0b43c7a36293df06f8fc5f.xml#id-a401626b1b0b43c7a36293df06f8fc5f"/>
    </sourceConnections>
    <sourceConnections
        xsi:type="archimate:DiagramModelArchimateConnection"
        id="id-6ab72c78dac1463da33ac1a14e9004af"
        font="1|Segoe UI|9.0|0|WINDOWS|1|-15|0|0|0|0|0|0|0|0|3|2|1|34|Segoe UI"
        source="id-f8ba8ff5d13641288d3c54dd9935a79b"
        target="id-73d2679b0cc349b5afa3e02cb4906db8">
      <archimateRelationship
          xsi:type="archimate:AggregationRelationship"
          href="AggregationRelationship_id-142fad66aeed4576a53da54b0b9d5335.xml#id-142fad66aeed4576a53da54b0b9d5335"/>
    </sourceConnections>
    <sourceConnections
        xsi:type="archimate:DiagramModelArchimateConnection"
        id="id-09b619f29d7d497685bfd845247af98e"
        font="1|Segoe UI|9.0|0|WINDOWS|1|-15|0|0|0|0|0|0|0|0|3|2|1|34|Segoe UI"
        source="id-f8ba8ff5d13641288d3c54dd9935a79b"
        target="id-24da8baebfe24aeba20a9e9fc9caa0dd">
      <archimateRelationship
          xsi:type="archimate:AggregationRelationship"
          href="AggregationRelationship_id-f83c0a447a714440916f0a24847f517e.xml#id-f83c0a447a714440916f0a24847f517e"/>
    </sourceConnections>
    <sourceConnections
        xsi:type="archimate:DiagramModelArchimateConnection"
        id="id-aa47435c077347c5a6a59a1cf3d43d68"
        font="1|Segoe UI|9.0|0|WINDOWS|1|-15|0|0|0|0|0|0|0|0|3|2|1|34|Segoe UI"
        source="id-f8ba8ff5d13641288d3c54dd9935a79b"
        target="id-84855ea42c124a9e8ef725dbf8f46750">
      <archimateRelationship
          xsi:type="archimate:AggregationRelationship"
          href="AggregationRelationship_id-2702c9190fd2455a99ce8d1f78656bef.xml#id-2702c9190fd2455a99ce8d1f78656bef"/>
    </sourceConnections>
    <sourceConnections
        xsi:type="archimate:DiagramModelArchimateConnection"
        id="id-472265d3610e40898648bbf96bec4be3"
        font="1|Segoe UI|9.0|0|WINDOWS|1|-15|0|0|0|0|0|0|0|0|3|2|1|34|Segoe UI"
        source="id-f8ba8ff5d13641288d3c54dd9935a79b"
        target="id-ee75d46249db45c39fabef159e284400">
      <archimateRelationship
          xsi:type="archimate:AggregationRelationship"
          href="AggregationRelationship_id-985afa020c864361813f9b39401f0f53.xml#id-985afa020c864361813f9b39401f0f53"/>
    </sourceConnections>
    <sourceConnections
        xsi:type="archimate:DiagramModelArchimateConnection"
        id="id-645ed37521974c5bb5a0c21813a65517"
        font="1|Segoe UI|9.0|0|WINDOWS|1|-15|0|0|0|0|0|0|0|0|3|2|1|34|Segoe UI"
        source="id-f8ba8ff5d13641288d3c54dd9935a79b"
        target="id-642d5c8d2039466c9d7e6619a456362e">
      <archimateRelationship
          xsi:type="archimate:AggregationRelationship"
          href="AggregationRelationship_id-01495ec3ec7a459aa4e06885d0c0633f.xml#id-01495ec3ec7a459aa4e06885d0c0633f"/>
    </sourceConnections>
    <sourceConnections
        xsi:type="archimate:DiagramModelArchimateConnection"
        id="id-94c1f45c6bac46b5a092297569c88fa1"
        font="1|Segoe UI|9.0|0|WINDOWS|1|-15|0|0|0|0|0|0|0|0|3|2|1|34|Segoe UI"
        source="id-f8ba8ff5d13641288d3c54dd9935a79b"
        target="id-71d7d7a3c7d74f28af67dc27af8ca12b">
      <archimateRelationship
          xsi:type="archimate:AggregationRelationship"
          href="AggregationRelationship_id-4173dc6f9c4646e39f539b70d4cc4558.xml#id-4173dc6f9c4646e39f539b70d4cc4558"/>
    </sourceConnections>
    <sourceConnections
        xsi:type="archimate:DiagramModelArchimateConnection"
        id="id-1985c4f7d23944b083de73d5242f57d2"
        font="1|Segoe UI|9.0|0|WINDOWS|1|-15|0|0|0|0|0|0|0|0|3|2|1|34|Segoe UI"
        source="id-f8ba8ff5d13641288d3c54dd9935a79b"
        target="id-b76b48f1d2bd4e7f866225ad74953e79">
      <archimateRelationship
          xsi:type="archimate:AggregationRelationship"
          href="AggregationRelationship_id-9643a88e47244d2a80769247d37c69f2.xml#id-9643a88e47244d2a80769247d37c69f2"/>
    </sourceConnections>
    <sourceConnections
        xsi:type="archimate:DiagramModelArchimateConnection"
        id="id-b3f4716dc4094a009a87ff86c9247108"
        font="1|Segoe UI|9.0|0|WINDOWS|1|-15|0|0|0|0|0|0|0|0|3|2|1|34|Segoe UI"
        source="id-f8ba8ff5d13641288d3c54dd9935a79b"
        target="id-c3dc826a8118435ab77a8e4e8cd131bc">
      <archimateRelationship
          xsi:type="archimate:AggregationRelationship"
          href="AggregationRelationship_id-a130b3322ec94c9d833d379c4e0de2cf.xml#id-a130b3322ec94c9d833d379c4e0de2cf"/>
    </sourceConnections>
    <sourceConnections
        xsi:type="archimate:DiagramModelArchimateConnection"
        id="id-02e414d79eab46c78610d8e9180153fa"
        font="1|Segoe UI|9.0|0|WINDOWS|1|-15|0|0|0|0|0|0|0|0|3|2|1|34|Segoe UI"
        source="id-f8ba8ff5d13641288d3c54dd9935a79b"
        target="id-413410348af948e9b2d8056ab7993871">
      <archimateRelationship
          xsi:type="archimate:AggregationRelationship"
          href="AggregationRelationship_id-6882c973067e4ea6957b8459578e41c3.xml#id-6882c973067e4ea6957b8459578e41c3"/>
    </sourceConnections>
    <bounds
        x="26"
        y="971"
        width="1480"
        height="153"/>
    <children
        xsi:type="archimate:DiagramModelArchimateObject"
        id="id-b76b48f1d2bd4e7f866225ad74953e79"
        targetConnections="id-1985c4f7d23944b083de73d5242f57d2"
        font="1|Segoe UI|9.0|0|WINDOWS|1|0|0|0|0|0|0|0|0|1|0|0|0|0|Segoe UI"
        fontColor="#000000"
        lineColor="#000000"
        fillColor="#ffffcc">
      <bounds
          x="1006"
          y="25"
          width="193"
          height="53"/>
      <archimateElement
          xsi:type="archimate:BusinessFunction"
          href="BusinessFunction_id-a08113886c6549f0a7c385c25e27d30b.xml#id-a08113886c6549f0a7c385c25e27d30b"/>
    </children>
    <children
        xsi:type="archimate:DiagramModelArchimateObject"
        id="id-71d7d7a3c7d74f28af67dc27af8ca12b"
        targetConnections="id-94c1f45c6bac46b5a092297569c88fa1"
        font="1|Segoe UI|9.0|0|WINDOWS|1|0|0|0|0|0|0|0|0|1|0|0|0|0|Segoe UI"
        fontColor="#000000"
        lineColor="#000000"
        fillColor="#ebc1a4">
      <bounds
          x="1008"
          y="86"
          width="193"
          height="53"/>
      <archimateElement
          xsi:type="archimate:BusinessFunction"
          href="BusinessFunction_id-0c183bd9261540fbb9c28d502a734014.xml#id-0c183bd9261540fbb9c28d502a734014"/>
    </children>
    <children
        xsi:type="archimate:DiagramModelArchimateObject"
        id="id-ee75d46249db45c39fabef159e284400"
        targetConnections="id-472265d3610e40898648bbf96bec4be3"
        font="1|Segoe UI|9.0|0|WINDOWS|1|0|0|0|0|0|0|0|0|1|0|0|0|0|Segoe UI"
        fontColor="#000000"
        lineColor="#000000"
        fillColor="#ebc1a4">
      <bounds
          x="762"
          y="86"
          width="193"
          height="53"/>
      <archimateElement
          xsi:type="archimate:BusinessFunction"
          href="BusinessFunction_id-a53576c6b2034f01b97b60291cc6fe1e.xml#id-a53576c6b2034f01b97b60291cc6fe1e"/>
    </children>
    <children
        xsi:type="archimate:DiagramModelArchimateObject"
        id="id-36e2f48e055c43dcaf43dfa9e88cbf3d"
        targetConnections="id-3414b24936784ad4b9e2b24319ebc11d"
        font="1|Segoe UI|9.0|0|WINDOWS|1|0|0|0|0|0|0|0|0|1|0|0|0|0|Segoe UI"
        fontColor="#000000"
        lineColor="#000000"
        fillColor="#ffffcc">
      <bounds
          x="522"
          y="86"
          width="193"
          height="53"/>
      <archimateElement
          xsi:type="archimate:BusinessFunction"
          href="BusinessFunction_id-fc47931269bb44cb9df6f1c7c17cc8a8.xml#id-fc47931269bb44cb9df6f1c7c17cc8a8"/>
    </children>
    <children
        xsi:type="archimate:DiagramModelArchimateObject"
        id="id-062b9dee702a443ba9c84ef1572d09b2"
        targetConnections="id-1238e56c5da243239a5934cfd733faf7"
        font="1|Segoe UI|9.0|0|WINDOWS|1|0|0|0|0|0|0|0|0|1|0|0|0|0|Segoe UI"
        fontColor="#000000"
        lineColor="#000000"
        fillColor="#ffffcc">
      <bounds
          x="275"
          y="86"
          width="193"
          height="53"/>
      <archimateElement
          xsi:type="archimate:BusinessFunction"
          href="BusinessFunction_id-7ed269b3167a43f38caf5795e6dc9685.xml#id-7ed269b3167a43f38caf5795e6dc9685"/>
    </children>
    <children
        xsi:type="archimate:DiagramModelArchimateObject"
        id="id-24da8baebfe24aeba20a9e9fc9caa0dd"
        targetConnections="id-09b619f29d7d497685bfd845247af98e"
        font="1|Segoe UI|9.0|0|WINDOWS|1|0|0|0|0|0|0|0|0|1|0|0|0|0|Segoe UI"
        fontColor="#000000"
        lineColor="#000000"
        fillColor="#ebc1a4">
      <bounds
          x="35"
          y="85"
          width="193"
          height="53"/>
      <archimateElement
          xsi:type="archimate:BusinessFunction"
          href="BusinessFunction_id-2c3635f84ede4f37a312d45d7a825c9c.xml#id-2c3635f84ede4f37a312d45d7a825c9c"/>
    </children>
    <children
        xsi:type="archimate:DiagramModelArchimateObject"
        id="id-84855ea42c124a9e8ef725dbf8f46750"
        targetConnections="id-aa47435c077347c5a6a59a1cf3d43d68"
        font="1|Segoe UI|9.0|0|WINDOWS|1|0|0|0|0|0|0|0|0|1|0|0|0|0|Segoe UI"
        fontColor="#000000"
        lineColor="#000000"
        fillColor="#ebc1a4">
      <bounds
          x="1248"
          y="86"
          width="193"
          height="53"/>
      <archimateElement
          xsi:type="archimate:BusinessFunction"
          href="BusinessFunction_id-5c2e5d0680c74423b2bdb636ae70986e.xml#id-5c2e5d0680c74423b2bdb636ae70986e"/>
    </children>
    <children
        xsi:type="archimate:DiagramModelArchimateObject"
        id="id-413410348af948e9b2d8056ab7993871"
        targetConnections="id-02e414d79eab46c78610d8e9180153fa"
        font="1|Segoe UI|9.0|0|WINDOWS|1|0|0|0|0|0|0|0|0|1|0|0|0|0|Segoe UI"
        fontColor="#000000"
        lineColor="#000000"
        fillColor="#ebc1a4">
      <bounds
          x="1248"
          y="25"
          width="193"
          height="53"/>
      <archimateElement
          xsi:type="archimate:BusinessFunction"
          href="BusinessFunction_id-36618f0c9efb4c278b2ea856bd1a628a.xml#id-36618f0c9efb4c278b2ea856bd1a628a"/>
    </children>
    <children
        xsi:type="archimate:DiagramModelArchimateObject"
        id="id-518b239032774056a23e0722b2841dcb"
        targetConnections="id-a67d3eef7f2b4bf1a0ff2f4c5019ea5f"
        font="1|Segoe UI|9.0|0|WINDOWS|1|0|0|0|0|0|0|0|0|1|0|0|0|0|Segoe UI"
        fontColor="#000000"
        lineColor="#000000"
        fillColor="#ffffcc">
      <bounds
          x="763"
          y="23"
          width="193"
          height="53"/>
      <archimateElement
          xsi:type="archimate:BusinessFunction"
          href="BusinessFunction_id-75d985aae94c44069597ef7be2c14525.xml#id-75d985aae94c44069597ef7be2c14525"/>
    </children>
    <children
        xsi:type="archimate:DiagramModelArchimateObject"
        id="id-73d2679b0cc349b5afa3e02cb4906db8"
        targetConnections="id-6ab72c78dac1463da33ac1a14e9004af"
        font="1|Segoe UI|9.0|0|WINDOWS|1|0|0|0|0|0|0|0|0|1|0|0|0|0|Segoe UI"
        fontColor="#000000"
        lineColor="#000000"
        fillColor="#ebc1a4">
      <bounds
          x="520"
          y="23"
          width="193"
          height="53"/>
      <archimateElement
          xsi:type="archimate:BusinessFunction"
          href="BusinessFunction_id-7b6415afa59e44288520743e19e2f139.xml#id-7b6415afa59e44288520743e19e2f139"/>
    </children>
    <children
        xsi:type="archimate:DiagramModelArchimateObject"
        id="id-642d5c8d2039466c9d7e6619a456362e"
        targetConnections="id-645ed37521974c5bb5a0c21813a65517"
        font="1|Segoe UI|9.0|0|WINDOWS|1|0|0|0|0|0|0|0|0|1|0|0|0|0|Segoe UI"
        fontColor="#000000"
        lineColor="#000000"
        fillColor="#ebc1a4">
      <bounds
          x="278"
          y="23"
          width="193"
          height="53"/>
      <archimateElement
          xsi:type="archimate:BusinessFunction"
          href="BusinessFunction_id-0f272ffc39c04a799971c6f454ab08cc.xml#id-0f272ffc39c04a799971c6f454ab08cc"/>
    </children>
    <children
        xsi:type="archimate:DiagramModelArchimateObject"
        id="id-c3dc826a8118435ab77a8e4e8cd131bc"
        targetConnections="id-b3f4716dc4094a009a87ff86c9247108"
        font="1|Segoe UI|9.0|0|WINDOWS|1|0|0|0|0|0|0|0|0|1|0|0|0|0|Segoe UI"
        fontColor="#000000"
        lineColor="#000000"
        fillColor="#ebc1a4">
      <bounds
          x="35"
          y="23"
          width="193"
          height="53"/>
      <archimateElement
          xsi:type="archimate:BusinessFunction"
          href="BusinessFunction_id-b4b48722621a4f15af0d9dffe6208414.xml#id-b4b48722621a4f15af0d9dffe6208414"/>
    </children>
    <archimateElement
        xsi:type="archimate:BusinessFunction"
        href="BusinessFunction_id-54ec41db61104ee09be092211e69037f.xml#id-54ec41db61104ee09be092211e69037f"/>
  </children>
</archimate:ArchimateDiagramModel>
